LICENSE.txt
MANIFEST.in
README.md
setup.py
bin/quantgo-service
bin/service_complete
quantgo_service_cli.egg-info/PKG-INFO
quantgo_service_cli.egg-info/SOURCES.txt
quantgo_service_cli.egg-info/dependency_links.txt
quantgo_service_cli.egg-info/requires.txt
quantgo_service_cli.egg-info/top_level.txt
service_cli/__init__.py
service_cli/cli.py
service_cli/client.py
service_cli/completer.py
service_cli/config.py
service_cli/errors.py
service_cli/qgservice.py
service_cli/schema.py
service_cli/service.py