Metadata-Version: 1.1
Name: quantgo-service-cli
Version: 2.1.1
Summary: QuantGo User Service Command Line Tool.
Home-page: https://quantgo.com
Author: Nikolay Krysiuk
Author-email: nikolay@quantgo.com
License: Copyright (c) 2013 QuantGo
